Functions_d/Functions_d.py
Functions_d/__init__.py
functions_d-1.28.dist-info/METADATA
functions_d-1.28.dist-info/WHEEL
functions_d-1.28.dist-info/top_level.txt
functions_d-1.28.dist-info/RECORD
