Metadata-Version: 2.4
Name: Functions_d
Version: 1.28
Summary: 包含数据处理、Hive交互、企业微信消息发送、Excel操作等功能的工具类库
Author: DongYang
Author-email: 649898871@qq.com
License: MIT
Classifier: Programming Language :: Python :: 3
Classifier: Programming Language :: Python :: 3.7
Classifier: Programming Language :: Python :: 3.8
Classifier: Programming Language :: Python :: 3.9
Classifier: Operating System :: Microsoft :: Windows
Classifier: Intended Audience :: Developers
Classifier: Topic :: Software Development :: Libraries :: Python Modules
Requires-Python: >=3.7
Requires-Dist: pandas>=1.3.0
Requires-Dist: numpy>=1.21.0
Requires-Dist: xlwings>=0.27.0
Requires-Dist: xlsxwriter>=3.0.0
Requires-Dist: yagmail>=0.15.293
Requires-Dist: requests>=2.26.0
Requires-Dist: pyhive>=0.6.5
Requires-Dist: thrift>=0.15.0
Requires-Dist: selenium>=4.0.0
Requires-Dist: webdriver-manager>=3.8.0
Requires-Dist: beautifulsoup4>=4.10.0
Requires-Dist: lxml>=4.6.3
Requires-Dist: pillow>=8.4.0
Requires-Dist: pypinyin>=0.48.0
Requires-Dist: psutil>=5.8.0
Requires-Dist: tenacity>=8.0.0
